docs/conf.py
praattools/__init__.py
praattools/file_io.py
praattools/interval.py
praat_tools-0.1.0.dist-info/METADATA
praat_tools-0.1.0.dist-info/WHEEL
praat_tools-0.1.0.dist-info/licenses/COPYING.md
praat_tools-0.1.0.dist-info/RECORD
